[
  {
    "ContainingType": "RegisterApi.Controllers.AdminProductController",
    "Method": "AddProduct",
    "RelativePath": "api/admin/add-product",
    "HttpMethod": "POST",
    "IsController": true,
    "Order": 0,
    "Parameters": [
      {
        "Name": "Title",
        "Type": "System.String",
        "IsRequired": false
      },
      {
        "Name": "Description",
        "Type": "System.String",
        "IsRequired": false
      },
      {
        "Name": "Price",
        "Type": "System.Decimal",
        "IsRequired": false
      },
      {
        "Name": "DiscountPercentage",
        "Type": "System.Double",
        "IsRequired": false
      },
      {
        "Name": "Rating",
        "Type": "System.Double",
        "IsRequired": false
      },
      {
        "Name": "Category",
        "Type": "System.String",
        "IsRequired": false
      },
      {
        "Name": "Brand",
        "Type": "System.String",
        "IsRequired": false
      },
      {
        "Name": "Thumbnail",
        "Type": "System.String",
        "IsRequired": false
      },
      {
        "Name": "ImageUrls",
        "Type": "System.Collections.Generic.List\u00601[[System.String, System.Private.CoreLib, Version=8.0.0.0, Culture=neutral, PublicKeyToken=7cec85d7bea7798e]]",
        "IsRequired": false
      },
      {
        "Name": "ImageFiles",
        "Type": "System.Collections.Generic.List\u00601[[Microsoft.AspNetCore.Http.IFormFile, Microsoft.AspNetCore.Http.Features, Version=8.0.0.0, Culture=neutral, PublicKeyToken=adb9793829ddae60]]",
        "IsRequired": false
      },
      {
        "Name": "Stock",
        "Type": "System.Int32",
        "IsRequired": false
      },
      {
        "Name": "Sku",
        "Type": "System.String",
        "IsRequired": false
      },
      {
        "Name": "AvailabilityStatus",
        "Type": "System.String",
        "IsRequired": false
      },
      {
        "Name": "SellerId",
        "Type": "System.Int32",
        "IsRequired": false
      }
    ],
    "ReturnTypes": []
  },
  {
    "ContainingType": "RegisterApi.Controllers.AdminProductController",
    "Method": "DeleteProduct",
    "RelativePath": "api/admin/delete-product/{id}",
    "HttpMethod": "DELETE",
    "IsController": true,
    "Order": 0,
    "Parameters": [
      {
        "Name": "id",
        "Type": "System.Int32",
        "IsRequired": true
      }
    ],
    "ReturnTypes": []
  },
  {
    "ContainingType": "RegisterApi.Controllers.AdminOrdersController",
    "Method": "GetAllOrders",
    "RelativePath": "api/admin/orders",
    "HttpMethod": "GET",
    "IsController": true,
    "Order": 0,
    "Parameters": [
      {
        "Name": "role",
        "Type": "System.String",
        "IsRequired": false
      },
      {
        "Name": "sellerId",
        "Type": "System.Int32",
        "IsRequired": false
      }
    ],
    "ReturnTypes": []
  },
  {
    "ContainingType": "RegisterApi.Controllers.AdminOrdersController",
    "Method": "MarkCodPaid",
    "RelativePath": "api/admin/orders/{id}/cod-paid",
    "HttpMethod": "PUT",
    "IsController": true,
    "Order": 0,
    "Parameters": [
      {
        "Name": "id",
        "Type": "System.Int32",
        "IsRequired": true
      }
    ],
    "ReturnTypes": []
  },
  {
    "ContainingType": "RegisterApi.Controllers.AdminOrdersController",
    "Method": "UpdateOrderStatus",
    "RelativePath": "api/admin/orders/{id}/status",
    "HttpMethod": "PUT",
    "IsController": true,
    "Order": 0,
    "Parameters": [
      {
        "Name": "id",
        "Type": "System.Int32",
        "IsRequired": true
      },
      {
        "Name": "status",
        "Type": "System.String",
        "IsRequired": true
      },
      {
        "Name": "role",
        "Type": "System.String",
        "IsRequired": false
      }
    ],
    "ReturnTypes": []
  },
  {
    "ContainingType": "RegisterApi.Controllers.AdminOrdersController",
    "Method": "VerifyPayment",
    "RelativePath": "api/admin/orders/{id}/verify-payment",
    "HttpMethod": "PUT",
    "IsController": true,
    "Order": 0,
    "Parameters": [
      {
        "Name": "id",
        "Type": "System.Int32",
        "IsRequired": true
      },
      {
        "Name": "role",
        "Type": "System.String",
        "IsRequired": false
      }
    ],
    "ReturnTypes": []
  },
  {
    "ContainingType": "RegisterApi.Controllers.AdminProductController",
    "Method": "UpdateProduct",
    "RelativePath": "api/admin/update-product/{id}",
    "HttpMethod": "PUT",
    "IsController": true,
    "Order": 0,
    "Parameters": [
      {
        "Name": "id",
        "Type": "System.Int32",
        "IsRequired": true
      },
      {
        "Name": "Title",
        "Type": "System.String",
        "IsRequired": false
      },
      {
        "Name": "Description",
        "Type": "System.String",
        "IsRequired": false
      },
      {
        "Name": "Price",
        "Type": "System.Decimal",
        "IsRequired": false
      },
      {
        "Name": "DiscountPercentage",
        "Type": "System.Double",
        "IsRequired": false
      },
      {
        "Name": "Rating",
        "Type": "System.Double",
        "IsRequired": false
      },
      {
        "Name": "Category",
        "Type": "System.String",
        "IsRequired": false
      },
      {
        "Name": "Brand",
        "Type": "System.String",
        "IsRequired": false
      },
      {
        "Name": "Thumbnail",
        "Type": "System.String",
        "IsRequired": false
      },
      {
        "Name": "ImageFiles",
        "Type": "System.Collections.Generic.List\u00601[[Microsoft.AspNetCore.Http.IFormFile, Microsoft.AspNetCore.Http.Features, Version=8.0.0.0, Culture=neutral, PublicKeyToken=adb9793829ddae60]]",
        "IsRequired": false
      },
      {
        "Name": "ImageUrls",
        "Type": "System.Collections.Generic.List\u00601[[System.String, System.Private.CoreLib, Version=8.0.0.0, Culture=neutral, PublicKeyToken=7cec85d7bea7798e]]",
        "IsRequired": false
      },
      {
        "Name": "Stock",
        "Type": "System.Int32",
        "IsRequired": false
      },
      {
        "Name": "Sku",
        "Type": "System.String",
        "IsRequired": false
      },
      {
        "Name": "AvailabilityStatus",
        "Type": "System.String",
        "IsRequired": false
      }
    ],
    "ReturnTypes": []
  },
  {
    "ContainingType": "RegisterApi.Controllers.AdminProductController",
    "Method": "GetProduct",
    "RelativePath": "api/editproduct/{id}",
    "HttpMethod": "GET",
    "IsController": true,
    "Order": 0,
    "Parameters": [
      {
        "Name": "id",
        "Type": "System.Int32",
        "IsRequired": true
      }
    ],
    "ReturnTypes": []
  },
  {
    "ContainingType": "RegisterApi.Controllers.ForgotPasswordController",
    "Method": "ResetPassword",
    "RelativePath": "api/ForgotPassword/reset",
    "HttpMethod": "POST",
    "IsController": true,
    "Order": 0,
    "Parameters": [
      {
        "Name": "req",
        "Type": "RegisterApi.Models.ResetPasswordRequest",
        "IsRequired": true
      }
    ],
    "ReturnTypes": []
  },
  {
    "ContainingType": "RegisterApi.Controllers.ForgotPasswordController",
    "Method": "SendOtp",
    "RelativePath": "api/ForgotPassword/send-otp",
    "HttpMethod": "POST",
    "IsController": true,
    "Order": 0,
    "Parameters": [
      {
        "Name": "req",
        "Type": "RegisterApi.Models.ForgotPasswordRequest",
        "IsRequired": true
      }
    ],
    "ReturnTypes": []
  },
  {
    "ContainingType": "RegisterApi.Controllers.ForgotPasswordController",
    "Method": "VerifyOtp",
    "RelativePath": "api/ForgotPassword/verify-otp",
    "HttpMethod": "POST",
    "IsController": true,
    "Order": 0,
    "Parameters": [
      {
        "Name": "req",
        "Type": "RegisterApi.Models.VerifyOtpRequest",
        "IsRequired": true
      }
    ],
    "ReturnTypes": []
  },
  {
    "ContainingType": "RegisterApi.Controllers.LoginController",
    "Method": "Login",
    "RelativePath": "api/Login/login",
    "HttpMethod": "POST",
    "IsController": true,
    "Order": 0,
    "Parameters": [
      {
        "Name": "user",
        "Type": "RegisterApi.Models.User",
        "IsRequired": true
      }
    ],
    "ReturnTypes": []
  },
  {
    "ContainingType": "RegisterApi.Controllers.MessagesController",
    "Method": "GetCustomerMessages",
    "RelativePath": "api/messages/customer/{email}/{productId}",
    "HttpMethod": "GET",
    "IsController": true,
    "Order": 0,
    "Parameters": [
      {
        "Name": "email",
        "Type": "System.String",
        "IsRequired": true
      },
      {
        "Name": "productId",
        "Type": "System.Int32",
        "IsRequired": true
      }
    ],
    "ReturnTypes": []
  },
  {
    "ContainingType": "RegisterApi.Controllers.MessagesController",
    "Method": "Reply",
    "RelativePath": "api/messages/reply/{id}",
    "HttpMethod": "PUT",
    "IsController": true,
    "Order": 0,
    "Parameters": [
      {
        "Name": "id",
        "Type": "System.Int32",
        "IsRequired": true
      },
      {
        "Name": "reply",
        "Type": "System.String",
        "IsRequired": true
      }
    ],
    "ReturnTypes": []
  },
  {
    "ContainingType": "RegisterApi.Controllers.MessagesController",
    "Method": "GetSellerMessages",
    "RelativePath": "api/messages/seller/{sellerId}",
    "HttpMethod": "GET",
    "IsController": true,
    "Order": 0,
    "Parameters": [
      {
        "Name": "sellerId",
        "Type": "System.Int32",
        "IsRequired": true
      }
    ],
    "ReturnTypes": []
  },
  {
    "ContainingType": "RegisterApi.Controllers.MessagesController",
    "Method": "SendMessage",
    "RelativePath": "api/messages/send",
    "HttpMethod": "POST",
    "IsController": true,
    "Order": 0,
    "Parameters": [
      {
        "Name": "msg",
        "Type": "RegisterApi.Models.SellerMessage",
        "IsRequired": true
      }
    ],
    "ReturnTypes": []
  },
  {
    "ContainingType": "RegisterApi.Controllers.OrdersController",
    "Method": "DeleteOrder",
    "RelativePath": "api/orders/{id}",
    "HttpMethod": "DELETE",
    "IsController": true,
    "Order": 0,
    "Parameters": [
      {
        "Name": "id",
        "Type": "System.Int32",
        "IsRequired": true
      },
      {
        "Name": "email",
        "Type": "System.String",
        "IsRequired": false
      }
    ],
    "ReturnTypes": []
  },
  {
    "ContainingType": "RegisterApi.Controllers.OrdersController",
    "Method": "GetOrderById",
    "RelativePath": "api/orders/detail/{id}",
    "HttpMethod": "GET",
    "IsController": true,
    "Order": 0,
    "Parameters": [
      {
        "Name": "id",
        "Type": "System.Int32",
        "IsRequired": true
      }
    ],
    "ReturnTypes": []
  },
  {
    "ContainingType": "RegisterApi.Controllers.OrdersController",
    "Method": "PlaceOrder",
    "RelativePath": "api/orders/place",
    "HttpMethod": "POST",
    "IsController": true,
    "Order": 0,
    "Parameters": [
      {
        "Name": "order",
        "Type": "RegisterApi.Models.Order",
        "IsRequired": true
      }
    ],
    "ReturnTypes": []
  },
  {
    "ContainingType": "RegisterApi.Controllers.OrdersController",
    "Method": "ReturnOrder",
    "RelativePath": "api/orders/return/{id}",
    "HttpMethod": "PUT",
    "IsController": true,
    "Order": 0,
    "Parameters": [
      {
        "Name": "id",
        "Type": "System.Int32",
        "IsRequired": true
      }
    ],
    "ReturnTypes": []
  },
  {
    "ContainingType": "RegisterApi.Controllers.OrdersController",
    "Method": "UpdateStatus",
    "RelativePath": "api/orders/status/{id}",
    "HttpMethod": "PUT",
    "IsController": true,
    "Order": 0,
    "Parameters": [
      {
        "Name": "id",
        "Type": "System.Int32",
        "IsRequired": true
      },
      {
        "Name": "status",
        "Type": "System.String",
        "IsRequired": false
      }
    ],
    "ReturnTypes": []
  },
  {
    "ContainingType": "RegisterApi.Controllers.OrdersController",
    "Method": "GetOrders",
    "RelativePath": "api/orders/user/{email}",
    "HttpMethod": "GET",
    "IsController": true,
    "Order": 0,
    "Parameters": [
      {
        "Name": "email",
        "Type": "System.String",
        "IsRequired": true
      }
    ],
    "ReturnTypes": []
  },
  {
    "ContainingType": "RegisterApi.Controllers.OrdersController",
    "Method": "VerifyPayment",
    "RelativePath": "api/orders/verify-payment/{id}",
    "HttpMethod": "PUT",
    "IsController": true,
    "Order": 0,
    "Parameters": [
      {
        "Name": "id",
        "Type": "System.Int32",
        "IsRequired": true
      },
      {
        "Name": "transactionId",
        "Type": "System.String",
        "IsRequired": false
      }
    ],
    "ReturnTypes": []
  },
  {
    "ContainingType": "ProductsController",
    "Method": "GetProductById",
    "RelativePath": "api/product/{id}",
    "HttpMethod": "GET",
    "IsController": true,
    "Order": 0,
    "Parameters": [
      {
        "Name": "id",
        "Type": "System.Int32",
        "IsRequired": true
      }
    ],
    "ReturnTypes": []
  },
  {
    "ContainingType": "ProductsController",
    "Method": "GetProducts",
    "RelativePath": "api/products",
    "HttpMethod": "GET",
    "IsController": true,
    "Order": 0,
    "Parameters": [],
    "ReturnTypes": []
  },
  {
    "ContainingType": "ProductsController",
    "Method": "UpdateProduct",
    "RelativePath": "api/products/{id}",
    "HttpMethod": "PUT",
    "IsController": true,
    "Order": 0,
    "Parameters": [
      {
        "Name": "id",
        "Type": "System.Int32",
        "IsRequired": true
      },
      {
        "Name": "Title",
        "Type": "System.String",
        "IsRequired": false
      },
      {
        "Name": "Description",
        "Type": "System.String",
        "IsRequired": false
      },
      {
        "Name": "Price",
        "Type": "System.Decimal",
        "IsRequired": false
      },
      {
        "Name": "DiscountPercentage",
        "Type": "System.Double",
        "IsRequired": false
      },
      {
        "Name": "Rating",
        "Type": "System.Double",
        "IsRequired": false
      },
      {
        "Name": "Category",
        "Type": "System.String",
        "IsRequired": false
      },
      {
        "Name": "Brand",
        "Type": "System.String",
        "IsRequired": false
      },
      {
        "Name": "Thumbnail",
        "Type": "System.String",
        "IsRequired": false
      },
      {
        "Name": "ImageFiles",
        "Type": "System.Collections.Generic.List\u00601[[Microsoft.AspNetCore.Http.IFormFile, Microsoft.AspNetCore.Http.Features, Version=8.0.0.0, Culture=neutral, PublicKeyToken=adb9793829ddae60]]",
        "IsRequired": false
      },
      {
        "Name": "ImageUrls",
        "Type": "System.Collections.Generic.List\u00601[[System.String, System.Private.CoreLib, Version=8.0.0.0, Culture=neutral, PublicKeyToken=7cec85d7bea7798e]]",
        "IsRequired": false
      },
      {
        "Name": "Stock",
        "Type": "System.Int32",
        "IsRequired": false
      },
      {
        "Name": "Sku",
        "Type": "System.String",
        "IsRequired": false
      },
      {
        "Name": "AvailabilityStatus",
        "Type": "System.String",
        "IsRequired": false
      },
      {
        "Name": "imageFiles",
        "Type": "System.Collections.Generic.List\u00601[[Microsoft.AspNetCore.Http.IFormFile, Microsoft.AspNetCore.Http.Features, Version=8.0.0.0, Culture=neutral, PublicKeyToken=adb9793829ddae60]]",
        "IsRequired": false
      }
    ],
    "ReturnTypes": []
  },
  {
    "ContainingType": "ProductsController",
    "Method": "DeleteProduct",
    "RelativePath": "api/products/{id}",
    "HttpMethod": "DELETE",
    "IsController": true,
    "Order": 0,
    "Parameters": [
      {
        "Name": "id",
        "Type": "System.Int32",
        "IsRequired": true
      }
    ],
    "ReturnTypes": []
  },
  {
    "ContainingType": "ProductsController",
    "Method": "GetProductsBySeller",
    "RelativePath": "api/products/seller/{sellerId}",
    "HttpMethod": "GET",
    "IsController": true,
    "Order": 0,
    "Parameters": [
      {
        "Name": "sellerId",
        "Type": "System.Int32",
        "IsRequired": true
      }
    ],
    "ReturnTypes": []
  },
  {
    "ContainingType": "RegisterApi.Controllers.RegisterController",
    "Method": "SendOtp",
    "RelativePath": "api/Register/send-otp",
    "HttpMethod": "POST",
    "IsController": true,
    "Order": 0,
    "Parameters": [
      {
        "Name": "req",
        "Type": "RegisterApi.Models.RegisterRequest",
        "IsRequired": true
      }
    ],
    "ReturnTypes": []
  },
  {
    "ContainingType": "RegisterApi.Controllers.RegisterController",
    "Method": "VerifyOtp",
    "RelativePath": "api/Register/verify-otp",
    "HttpMethod": "POST",
    "IsController": true,
    "Order": 0,
    "Parameters": [
      {
        "Name": "req",
        "Type": "RegisterApi.Models.VerifyOtpRequest",
        "IsRequired": true
      }
    ],
    "ReturnTypes": []
  },
  {
    "ContainingType": "RegisterApi.Controllers.ResetPasswordController",
    "Method": "ResetPassword",
    "RelativePath": "api/ResetPassword/reset",
    "HttpMethod": "POST",
    "IsController": true,
    "Order": 0,
    "Parameters": [
      {
        "Name": "req",
        "Type": "RegisterApi.Models.ResetPasswordRequest",
        "IsRequired": true
      }
    ],
    "ReturnTypes": []
  },
  {
    "ContainingType": "RegisterApi.Controllers.ResetPasswordController",
    "Method": "VerifyOtp",
    "RelativePath": "api/ResetPassword/verify-otp",
    "HttpMethod": "POST",
    "IsController": true,
    "Order": 0,
    "Parameters": [
      {
        "Name": "req",
        "Type": "RegisterApi.Models.VerifyOtpRequest",
        "IsRequired": true
      }
    ],
    "ReturnTypes": []
  },
  {
    "ContainingType": "RegisterApi.Controllers.SearchController",
    "Method": "Search",
    "RelativePath": "api/search",
    "HttpMethod": "GET",
    "IsController": true,
    "Order": 0,
    "Parameters": [
      {
        "Name": "q",
        "Type": "System.String",
        "IsRequired": false
      }
    ],
    "ReturnTypes": []
  },
  {
    "ContainingType": "RegisterApi.Controllers.SocialController",
    "Method": "GoogleLogin",
    "RelativePath": "api/social/google-login",
    "HttpMethod": "POST",
    "IsController": true,
    "Order": 0,
    "Parameters": [
      {
        "Name": "req",
        "Type": "RegisterApi.Controllers.GoogleAuthRequest",
        "IsRequired": true
      }
    ],
    "ReturnTypes": []
  },
  {
    "ContainingType": "RegisterApi.Controllers.SocialController",
    "Method": "GoogleSignup",
    "RelativePath": "api/social/google-signup",
    "HttpMethod": "POST",
    "IsController": true,
    "Order": 0,
    "Parameters": [
      {
        "Name": "req",
        "Type": "RegisterApi.Controllers.GoogleAuthRequest",
        "IsRequired": true
      }
    ],
    "ReturnTypes": []
  },
  {
    "ContainingType": "RegisterApi.Controllers.WeatherForecastController",
    "Method": "Get",
    "RelativePath": "WeatherForecast",
    "HttpMethod": "GET",
    "IsController": true,
    "Order": 0,
    "Parameters": [],
    "ReturnTypes": [
      {
        "Type": "System.Collections.Generic.IEnumerable\u00601[[RegisterApi.WeatherForecast, RegisterApi, Version=1.0.0.0, Culture=neutral, PublicKeyToken=null]]",
        "MediaTypes": [
          "text/plain",
          "application/json",
          "text/json"
        ],
        "StatusCode": 200
      }
    ],
    "EndpointName": "GetWeatherForecast"
  }
]